MANIFEST.in
setup.py
Products/__init__.py
Products.SilvaNews.egg-info/PKG-INFO
Products.SilvaNews.egg-info/SOURCES.txt
Products.SilvaNews.egg-info/dependency_links.txt
Products.SilvaNews.egg-info/entry_points.txt
Products.SilvaNews.egg-info/namespace_packages.txt
Products.SilvaNews.egg-info/not-zip-safe
Products.SilvaNews.egg-info/requires.txt
Products.SilvaNews.egg-info/top_level.txt
Products/SilvaNews/AgendaItem.py
Products/SilvaNews/CREDITS.txt
Products/SilvaNews/HISTORY.txt
Products/SilvaNews/LICENSE.txt
Products/SilvaNews/NewsCategorization.py
Products/SilvaNews/NewsItem.py
Products/SilvaNews/README.txt
Products/SilvaNews/__init__.py
Products/SilvaNews/configure.zcml
Products/SilvaNews/ftesting.zcml
Products/SilvaNews/installer.py
Products/SilvaNews/interfaces.py
Products/SilvaNews/newsitem.xslt
Products/SilvaNews/testing.py
Products/SilvaNews/silvaxml/__init__.py
Products/SilvaNews/silvaxml/helpers.py
Products/SilvaNews/silvaxml/xmlexport.py
Products/SilvaNews/silvaxml/xmlimport.py
Products/SilvaNews/tests/__init__.py
Products/SilvaNews/tests/test_upgrader.py
Products/SilvaNews/upgrader/__init__.py
Products/SilvaNews/upgrader/upgrade_220.py
Products/SilvaNews/upgrader/upgrade_230.py
Products/SilvaNews/upgrader/upgrade_236.py
Products/SilvaNews/upgrader/upgrade_300.py
Products/SilvaNews/www/agenda_item.png
Products/SilvaNews/www/news_item.png