Metadata-Version: 1.1
Name: Products.SilvaNews
Version: 3.0.1
Summary: News extension for Silva 2.x.
Home-page: https://github.com/silvacms/Products.SilvaNews
Author: Infrae
Author-email: info@infrae.com
License: BSD
Keywords: news silva zope2
Platform: UNKNOWN
Classifier: Framework :: Zope2
Classifier: Topic :: Internet :: WWW/HTTP :: Dynamic Content :: Message Boards
Classifier: Programming Language :: Python
Classifier: Topic :: Software Development :: Libraries :: Python Modules
